MANIFEST.in
README.md
kale.py
setup.py
kale.egg-info/PKG-INFO
kale.egg-info/SOURCES.txt
kale.egg-info/dependency_links.txt
kale.egg-info/requires.txt
kale.egg-info/top_level.txt