Metadata-Version: 1.0
Name: kale
Version: 0.2.3
Summary: Tiny PyMongo model layer
Home-page: https://github.com/Calama/kale
Author: Philip Schleihauf
Author-email: uniphil@gmail.com
License: :) released by Calama Consulting
Platform: UNKNOWN
